LICENSE
MANIFEST.in
NOTICE
README.rst
requirements.txt
setup.py
openfermionprojectq/__init__.py
openfermionprojectq/_demo_test.py
openfermionprojectq/_ffft.py
openfermionprojectq/_ffft_test.py
openfermionprojectq/_graph.py
openfermionprojectq/_graph_test.py
openfermionprojectq/_low_depth_trotter_simulation.py
openfermionprojectq/_low_depth_trotter_simulation_test.py
openfermionprojectq/_parallel_bubble_sort.py
openfermionprojectq/_parallel_bubble_sort_test.py
openfermionprojectq/_time_evolution.py
openfermionprojectq/_time_evolution_test.py
openfermionprojectq/_unitary_cc.py
openfermionprojectq/_unitary_cc_test.py
openfermionprojectq/_version.py
openfermionprojectq.egg-info/PKG-INFO
openfermionprojectq.egg-info/SOURCES.txt
openfermionprojectq.egg-info/dependency_links.txt
openfermionprojectq.egg-info/requires.txt
openfermionprojectq.egg-info/top_level.txt