Metadata-Version: 1.0
Name: openfermionprojectq
Version: 0.2
Summary: A plugin allowing OpenFermion to interaface with ProjectQ.
Home-page: http://www.openfermion.org
Author: The OpenFermion Developers
Author-email: help@openfermion.org
License: Apache 2
Platform: UNKNOWN
